rstatic/__init__.py
rstatic/application.py
rstatic-0.0.2.dist-info/LICENSE.md
rstatic-0.0.2.dist-info/METADATA
rstatic-0.0.2.dist-info/WHEEL
rstatic-0.0.2.dist-info/top_level.txt
rstatic-0.0.2.dist-info/RECORD
