Metadata-Version: 2.1
Name: rstatic
Version: 0.0.2
Summary: Open-source static site generator.
Home-page: https://rebatch.io/rstatic
Author: Joshua Powell
Author-email: UNKNOWN
License: UNKNOWN
Platform: UNKNOWN
Classifier: Programming Language :: Python :: 3
Classifier: License :: OSI Approved :: GNU Affero General Public License v3 or later (AGPLv3+)
Classifier: Operating System :: POSIX :: Linux
Classifier: Framework :: Flask
Classifier: Natural Language :: English
Classifier: Topic :: Software Development :: Libraries :: Application Frameworks
Requires-Dist: flask
Requires-Dist: frozen-flask
Requires-Dist: flask-flatpages
